atmolib/__init__.py
atmolib/base.py
atmolib/errors.py
atmolib/version.py
atmolib/weather_codes.json
atmolib/common/__init__.py
atmolib/common/constants.py
atmolib/common/tools.py
atmolib/meteorology/__init__.py
atmolib/meteorology/air.py
atmolib/meteorology/archive.py
atmolib/meteorology/marine.py
atmolib/meteorology/weather.py
tests/__init__.py
tests/conftest.py
tests/test_tools.py
tests/utils.py
tests/meteorology/__init__.py
tests/meteorology/conftest.py
tests/meteorology/test_air.py
tests/meteorology/test_archive.py
tests/meteorology/test_marine.py
tests/meteorology/test_weather.py
atmolib-0.1.1.dist-info/LICENSE
atmolib-0.1.1.dist-info/METADATA
atmolib-0.1.1.dist-info/WHEEL
atmolib-0.1.1.dist-info/top_level.txt
atmolib-0.1.1.dist-info/RECORD
