Metadata-Version: 2.1
Name: atmolib
Version: 0.1.1
Summary: Versatile weather package for effortless meteorology data extraction.
Home-page: https://www.github.com/rahul4732saini/atmolib
Author: rahul4732saini
Author-email: rahul4732saini@gmail.com
License: MIT
Keywords: atmolib,weather,meteorology,pandas,open-meteo
Platform: any
Classifier: License :: OSI Approved :: MIT License
Classifier: Intended Audience :: Developers
Classifier: Operating System :: OS Independent
Classifier: Development Status :: 4 - Beta
Classifier: Topic :: Scientific/Engineering :: Atmospheric Science
Classifier: Topic :: Software Development :: Libraries
Classifier: Topic :: Software Development :: Libraries :: Python Modules
Classifier: Programming Language :: Python :: 3.10
Classifier: Programming Language :: Python :: 3.11
Classifier: Programming Language :: Python :: 3.12
License-File: LICENSE
Requires-Dist: certifi==2024.7.4
Requires-Dist: charset-normalizer==3.3.2
Requires-Dist: idna==3.7
Requires-Dist: numpy==1.26.4
Requires-Dist: pandas==2.2.2
Requires-Dist: python-dateutil==2.9.0.post0
Requires-Dist: pytz==2024.1
Requires-Dist: requests==2.32.2
Requires-Dist: six==1.16.0
Requires-Dist: tzdata==2024.1
Requires-Dist: urllib3==2.2.2
